urdf2webots/__init__.py
urdf2webots/gazebo_materials.py
urdf2webots/importer.py
urdf2webots/math_utils.py
urdf2webots/parserURDF.py
urdf2webots/writeRobot.py
urdf2webots-2025.0.0.dist-info/LICENSE
urdf2webots-2025.0.0.dist-info/METADATA
urdf2webots-2025.0.0.dist-info/WHEEL
urdf2webots-2025.0.0.dist-info/top_level.txt
urdf2webots-2025.0.0.dist-info/RECORD
