Metadata-Version: 2.2
Name: urdf2webots
Version: 2025.0.0
Summary: A converter between URDF and PROTO files.
Home-page: https://github.com/cyberbotics/urdf2webots
Author: Cyberbotics
Author-email: support@cyberbotics.com
License: Apache License, Version 2.0
Classifier: Intended Audience :: Developers
Classifier: License :: OSI Approved :: Apache Software License
Classifier: Programming Language :: Python
Classifier: Topic :: Software Development
License-File: LICENSE
Requires-Dist: Pillow
Requires-Dist: numpy
Requires-Dist: rospkg
Dynamic: author
Dynamic: author-email
Dynamic: classifier
Dynamic: description
Dynamic: description-content-type
Dynamic: home-page
Dynamic: license
Dynamic: requires-dist
Dynamic: summary
